uploadi/__init__.py
uploadi/uploadi.py
uploadi-2.0.1.dist-info/licenses/LICENSE.txt
uploadi-2.0.1.dist-info/METADATA
uploadi-2.0.1.dist-info/WHEEL
uploadi-2.0.1.dist-info/entry_points.txt
uploadi-2.0.1.dist-info/top_level.txt
uploadi-2.0.1.dist-info/RECORD
