Metadata-Version: 2.4
Name: uploadi
Version: 2.0.1
Summary: Приложение для загрузки проектов python
Author: Ilia Miheev
Author-email: waggle-pout-sprawl@duck.com
License: MIT
License-File: LICENSE.txt
Requires-Dist: setuptools
Dynamic: author
Dynamic: author-email
Dynamic: description
Dynamic: description-content-type
Dynamic: license
Dynamic: license-file
Dynamic: requires-dist
Dynamic: summary
